README.rst
setup.py
src/platformrun/__init__.py
src/platformrun/detect.py
src/platformrun/platformrun.py
src/pyenergy/__init__.py
src/pyenergy/interactive_graph.py
src/pyenergy/pyenergy.py
src/pyenergy/test.py
src/pyenergy/tools.py
src/pyenergy/upgrade.py
src/pyenergy.egg-info/PKG-INFO
src/pyenergy.egg-info/SOURCES.txt
src/pyenergy.egg-info/dependency_links.txt
src/pyenergy.egg-info/entry_points.txt
src/pyenergy.egg-info/requires.txt
src/pyenergy.egg-info/top_level.txt
src/pyenergy.egg-info/zip-safe