Metadata-Version: 1.0
Name: pyenergy
Version: 0.1rc13
Summary: An interface to the MAGEEC energy monitor boards
Home-page: UNKNOWN
Author: James Pallister
Author-email: james.pallister@bristol.ac.uk
License: LGPL
Keywords: energy monitor MAGEEC
Platform: UNKNOWN
